lib_dzne_manifesto/__init__.py
lib_dzne_manifesto/manifesto/Prog.py
lib_dzne_manifesto/manifesto/__init__.py
lib_dzne_manifesto/manifesto/chain.py
lib_dzne_manifesto/manifesto/elemkey.py
lib_dzne_manifesto/manifesto/masterfile.py
lib_dzne_manifesto/manifesto/slim.py
lib_dzne_manifesto-0.2.1.dist-info/LICENSE.txt
lib_dzne_manifesto-0.2.1.dist-info/METADATA
lib_dzne_manifesto-0.2.1.dist-info/WHEEL
lib_dzne_manifesto-0.2.1.dist-info/top_level.txt
lib_dzne_manifesto-0.2.1.dist-info/RECORD
