Metadata-Version: 2.1
Name: lib-dzne-manifesto
Version: 0.2.1
Summary: lib_dzne_manifesto
Author-email: Johannes <johannes-programming@posteo.org>
Project-URL: Download, https://pypi.org/project/lib-dzne-manifesto/#files
Project-URL: Source, https://github.com/johannes-programming/lib_dzne_manifesto
Classifier: License :: OSI Approved :: MIT License
Classifier: Programming Language :: Python
Classifier: Programming Language :: Python :: 3
Requires-Python: >=3.11
License-File: LICENSE.txt
Requires-Dist: na-quantors >=1.0
